<Annotation><filename>01556</filename><size><width>1920</width><height>1080</height><depth>3</depth></size><object><name>car</name><pose>Unspecified</pose><truncated>0</truncated><difficult>0</difficult><bndbox><xmin>955</xmin><ymin>855</ymin><xmax>1264</xmax><ymax>1017</ymax></bndbox></object><object><name>car</name><pose>Unspecified</pose><truncated>0</truncated><difficult>0</difficult><bndbox><xmin>1103</xmin><ymin>720</ymin><xmax>1385</xmax><ymax>852</ymax></bndbox></object><object><name>person</name><pose>Unspecified</pose><truncated>0</truncated><difficult>0</difficult><bndbox><xmin>718</xmin><ymin>344</ymin><xmax>740</xmax><ymax>406</ymax></bndbox></object><object><name>person</name><pose>Unspecified</pose><truncated>0</truncated><difficult>0</difficult><bndbox><xmin>805</xmin><ymin>337</ymin><xmax>835</xmax><ymax>401</ymax></bndbox></object><object><name>car</name><pose>Unspecified</pose><truncated>0</truncated><difficult>0</difficult><bndbox><xmin>1432</xmin><ymin>982</ymin><xmax>1792</xmax><ymax>1079</ymax></bndbox></object><object><name>person</name><pose>Unspecified</pose><truncated>0</truncated><difficult>0</difficult><bndbox><xmin>1567</xmin><ymin>702</ymin><xmax>1617</xmax><ymax>798</ymax></bndbox></object><object><name>car</name><pose>Unspecified</pose><truncated>0</truncated><difficult>0</difficult><bndbox><xmin>1</xmin><ymin>493</ymin><xmax>60</xmax><ymax>572</ymax></bndbox></object><object><name>car</name><pose>Unspecified</pose><truncated>0</truncated><difficult>0</difficult><bndbox><xmin>433</xmin><ymin>84</ymin><xmax>574</xmax><ymax>154</ymax></bndbox></object><object><name>car</name><pose>Unspecified</pose><truncated>0</truncated><difficult>0</difficult><bndbox><xmin>5</xmin><ymin>332</ymin><xmax>495</xmax><ymax>590</ymax></bndbox></object><object><name>car</name><pose>Unspecified</pose><truncated>0</truncated><difficult>0</difficult><bndbox><xmin>359</xmin><ymin>258</ymin><xmax>578</xmax><ymax>364</ymax></bndbox></object><object><name>car</name><pose>Unspecified</pose><truncated>0</truncated><difficult>0</difficult><bndbox><xmin>318</xmin><ymin>825</ymin><xmax>746</xmax><ymax>1053</ymax></bndbox></object><object><name>person</name><pose>Unspecified</pose><truncated>0</truncated><difficult>0</difficult><bndbox><xmin>1293</xmin><ymin>654</ymin><xmax>1355</xmax><ymax>746</ymax></bndbox></object><object><name>person</name><pose>Unspecified</pose><truncated>0</truncated><difficult>0</difficult><bndbox><xmin>1442</xmin><ymin>675</ymin><xmax>1480</xmax><ymax>765</ymax></bndbox></object><object><name>person</name><pose>Unspecified</pose><truncated>0</truncated><difficult>0</difficult><bndbox><xmin>1753</xmin><ymin>769</ymin><xmax>1798</xmax><ymax>832</ymax></bndbox></object></Annotation>